bulkmail/__init__.py
bulkmail/commandline.py
bulkmail/extras.py
bulkmail/mailer.py
bulkmail/mailfunctions.py
bulkmail-1.1.0.dist-info/LICENSE
bulkmail-1.1.0.dist-info/METADATA
bulkmail-1.1.0.dist-info/WHEEL
bulkmail-1.1.0.dist-info/entry_points.txt
bulkmail-1.1.0.dist-info/top_level.txt
bulkmail-1.1.0.dist-info/RECORD
